tic_tac_toe_3x3/__init__.py
tic_tac_toe_3x3/play.py
tic_tac_toe_3x3/console_simple/__init__.py
tic_tac_toe_3x3/console_simple/__main__.py
tic_tac_toe_3x3/console_simple/args.py
tic_tac_toe_3x3/console_simple/cli.py
tic_tac_toe_3x3/console_simple/players.py
tic_tac_toe_3x3/console_simple/renderers.py
tic_tac_toe_3x3/game/__init__.py
tic_tac_toe_3x3/game/engine.py
tic_tac_toe_3x3/game/players.py
tic_tac_toe_3x3/game/renderers.py
tic_tac_toe_3x3/logic/__init__.py
tic_tac_toe_3x3/logic/exceptions.py
tic_tac_toe_3x3/logic/minimax.py
tic_tac_toe_3x3/logic/models.py
tic_tac_toe_3x3/logic/validators.py
tic_tac_toe_3x3-1.1.0.dist-info/licenses/LICENSE
tic_tac_toe_3x3-1.1.0.dist-info/METADATA
tic_tac_toe_3x3-1.1.0.dist-info/WHEEL
tic_tac_toe_3x3-1.1.0.dist-info/entry_points.txt
tic_tac_toe_3x3-1.1.0.dist-info/top_level.txt
tic_tac_toe_3x3-1.1.0.dist-info/RECORD
