Metadata-Version: 2.4
Name: tic_tac_toe_3x3
Version: 1.1.0
Summary: A simple tic-tac-toe game for 2 players and 3x3 field.
Author-email: Kostyantyn Zivenko <kos.zivenko@gmail.com>, Real Python <info@realpython.com>
License: The MIT License (MIT)
Project-URL: Repository, https://github.com/KonstZiv/little-tic-tac-toe
Keywords: tic-tac-toe,game,3x3,python,education,tutorial,asyncio
Classifier: Topic :: Education
Classifier: Topic :: Games/Entertainment
Classifier: Topic :: Software Development
Classifier: Programming Language :: Python :: 3
Requires-Python: >=3.11.0
License-File: LICENSE
Provides-Extra: dev
Requires-Dist: black; extra == "dev"
Requires-Dist: flake8; extra == "dev"
Requires-Dist: isort; extra == "dev"
Requires-Dist: pytest; extra == "dev"
Dynamic: license-file
